tests/__init__.py
tests/conftest.py
tests/settings.py
tests/test_page.py
tests/urls.py
tests/testapp/__init__.py
tests/testapp/apps.py
tests/testapp/models.py
tests/testapp/migrations/0001_initial.py
tests/testapp/migrations/0002_create_simplepage.py
tests/testapp/migrations/__init__.py
wagtailaccessibility/__init__.py
wagtailaccessibility/jinja2tags.py
wagtailaccessibility/static/js/tota11y.min.js
wagtailaccessibility/templates/wagtailaccessibility/tota11y.html
wagtailaccessibility/templatetags/__init__.py
wagtailaccessibility/templatetags/wagtailaccessibility_tags.py
wagtail_accessibility-2.0.0.dist-info/LICENSE
wagtail_accessibility-2.0.0.dist-info/METADATA
wagtail_accessibility-2.0.0.dist-info/WHEEL
wagtail_accessibility-2.0.0.dist-info/top_level.txt
wagtail_accessibility-2.0.0.dist-info/RECORD
